collect_photos/__init__.py
collect_photos/aws.py
collect_photos/collect_photos.py
collect_photos/mounting.py
collect_photos-0.0.0.data/scripts/collect-photos
collect_photos-0.0.0.dist-info/METADATA
collect_photos-0.0.0.dist-info/WHEEL
collect_photos-0.0.0.dist-info/top_level.txt
collect_photos-0.0.0.dist-info/RECORD
