Metadata-Version: 2.1
Name: collect-photos
Version: 0.0.0
Summary: Uploading Files to AWS S3 and Logging it into DynamoDB
Home-page: UNKNOWN
Author: Matthew Wen
Author-email: mattwen2018@gmail.com
License: UNKNOWN
Platform: UNKNOWN
Classifier: Programming Language :: Python
Classifier: Programming Language :: Python :: 3
Classifier: Programming Language :: Python :: 3.6
Classifier: Programming Language :: Python :: 3.7
Classifier: Programming Language :: Python :: 3.8
Requires-Dist: boto3 (>=1.14.23)
Requires-Dist: pytest (>=5.4.3)
